flask_order/__init__.py
flask_order/order.py
flask_ordering-0.0.2.dist-info/LICENSE
flask_ordering-0.0.2.dist-info/METADATA
flask_ordering-0.0.2.dist-info/WHEEL
flask_ordering-0.0.2.dist-info/top_level.txt
flask_ordering-0.0.2.dist-info/RECORD
