Metadata-Version: 2.1
Name: flask-ordering
Version: 0.0.2
Summary: flask-rest-api reponse ordering
Home-page: 
Author: Sandakin Gunadasa
Author-email: sandakinh@gmail.com
License: UNKNOWN
Platform: UNKNOWN
Classifier: Programming Language :: Python :: 3
Classifier: License :: OSI Approved :: MIT License
Classifier: Operating System :: OS Independent
